pnodes/__init__.py
pnodes/pnodes.py
pnodes/utils.py
pnodes/terminal/__init__.py
pnodes/terminal/client.py
pnodes/terminal/utils.py
pnodes/terminal/cap/__init__.py
pnodes/terminal/cap/command.py
pnodes/terminal/list/__init__.py
pnodes/terminal/list/command.py
pnodes/terminal/total/__init__.py
pnodes/terminal/total/command.py
scripts/__init__.py
scripts/pnodes.py
pnodes-0.1.dist-info/LICENSE
pnodes-0.1.dist-info/METADATA
pnodes-0.1.dist-info/WHEEL
pnodes-0.1.dist-info/entry_points.txt
pnodes-0.1.dist-info/top_level.txt
pnodes-0.1.dist-info/RECORD
